{
  "versionCode": "74750110",
  "versionName": "7.47.0.74750110",
  "downloadLink": "https://alabidimods.com/snaptube-pro/",
  "forceUpdate": false,
  "Title": "Snaptube Pro Premium Features!",
  "Msg": "التحديث للإصدار 7.47.0.74750110\n\n✨ جديد في Snaptube Pro:\n\n✅ تحميل الفيديوهات بجودة تصل إلى 4K\n✅ تنزيل الصوت MP3 مباشرة من أي فيديو\n✅ دعم أكثر من 50 منصة (YouTube، Facebook، TikTok، Instagram...)\n✅ سرعة تحميل فائقة بدون تقطيع\n✅ مشاهدة الفيديوهات بدون إنترنت بعد التحميل\n✅ إزالة الإعلانات بشكل كامل (نسخة VIP)\n✅ واجهة سهلة وسلسة تدعم الوضع الليلي\n✅ دعم تحميل متعدد في نفس الوقت\n✅ إدارة وتنظيم الملفات داخل التطبيق\n✅ مشغل مدمج للفيديو والصوت\n✅ نسخة كاملة ومدفوعة Premium & VIP مجانية",
  "updateSize": "25.49M",
  "releaseDate": "2025-09-21",
  "priority": "high"
}